Serdes/enable.sv
module sp_enable(
	input clk,
  	input reset,
  	input en,
  	output reg sp_en
);
  always@(posedge clk)
    begin
      if(reset)
        sp_en<=1'b0;
      else
        sp_en<=((en==0)?1:0);
    end
endmodule

Serdes/reg_8.sv
module reg_8 (
    input clk,
    input reset,
    input data_en,
    input [7:0] din,
    output reg [7:0] dout
  );
  always @(posedge clk or negedge reset)
  begin
    if(!reset)
    begin
      dout<= 8'h00;
    end
    else
      if(data_en)
      begin
        dout <=din;
      end
      else
        dout <= dout;
  end
endmodule
`default_nettype wire

Serdes/decoder.sv
module decoder (
    input clk,
    input reset,
    input [9:0] din,
    input dec_en,
    output reg [7:0] dout
  );
  reg [2:0] temp_3;
  reg [4:0] temp_5;
  reg [3:0] count;

  always @ (posedge clk or negedge reset)
  begin
    if (!reset)
    begin
      temp_3 <= 3'b000;
      temp_5 <= 5'b00000;
      dout <= 10'h0; // Reset dout
    end
    else
    begin
      if(dec_en)
      begin
        case (din[9:6])
          4'b0100:
            temp_3 <= 3'b000;
          4'b1001:
            temp_3 <= 3'b001;
          4'b0101:
            temp_3 <= 3'b010;
          4'b0011:
            temp_3 <= 3'b011;
          4'b0010:
            temp_3 <= 3'b100;
          4'b1010:
            temp_3 <= 3'b101;
          4'b0110:
            temp_3 <= 3'b110;
          4'b0001:
            temp_3 <= 3'b111;
          default:
            temp_3 <= 3'b000;
        endcase
        case (din[5:0])
          6'b011000:
            temp_5 <= 5'b00000;
          6'b011101:
            temp_5 <= 5'b00001;
          6'b010010:
            temp_5 <= 5'b00010;
          6'b110001:
            temp_5 <= 5'b00011;
          6'b110101:
            temp_5 <= 5'b00100;
          6'b101001:
            temp_5 <= 5'b00101;
          6'b011001:
            temp_5 <= 5'b00110;
          6'b111000:
            temp_5 <= 5'b00111;
          6'b111001:
            temp_5 <= 5'b01000;
          6'b100101:
            temp_5 <= 5'b01001;
          6'b010101:
            temp_5 <= 5'b01010;
          6'b110100:
            temp_5<= 5'b01011;
          6'b001101:
            temp_5 <= 5'b01100;
          6'b101100:
            temp_5 <= 5'b01101;
          6'b011100:
            temp_5 <= 5'b01110;
          6'b010111:
            temp_5 <= 5'b01111;
          6'b011011:
            temp_5 <= 5'b10000;
          6'b100011:
            temp_5 <= 5'b10001;
          6'b010011:
            temp_5 <= 5'b10010;
          6'b110010:
            temp_5 <= 5'b10011;
          6'b001011:
            temp_5 <= 5'b10100;
          6'b101010:
            temp_5 <= 5'b10101;
          6'b011010:
            temp_5 <= 5'b10110;
          6'b111010:
            temp_5 <= 5'b10111;
          6'b110011:
            temp_5 <= 5'b11000;
          6'b100110:
            temp_5 <= 5'b11001;
          6'b010110:
            temp_5 <= 5'b11010;
          6'b110110:
            temp_5 <= 5'b11011;
          6'b001110:
            temp_5 <= 5'b11100;
          6'b101110:
            temp_5 <= 5'b11101;
          6'b011110:
            temp_5 <= 5'b11110;
          6'b101011:
            temp_5 <= 5'b11111;
          default:
            temp_5 <= 5'b00000;
        endcase
        
      end
      //else dout <= {temp_3, temp_5};
    end
  end
  always @(posedge clk) begin
    if (dec_en) begin
      dout <= {temp_3, temp_5}; // Update dout when enc_en is high
        end
    end
endmodule

Serdes/reg_10.sv
module reg_10 (
    input clk,
    input reset,
    input data_en,
    input [9:0] din,
    output reg [9:0] dout
  );
  always @(posedge clk or negedge reset)
  begin
    if(!reset)
    begin
      dout<= 10'h00;
    end
    else
      if(data_en)
      begin
        dout <=din;
      end
      else
        dout <= dout;
  end
endmodule
`default_nettype wire

Serdes/sipo.sv
module sipo (
  input clk,
  input reset,
  input din,
  input shift,
  output reg deco,
  output reg [9:0] dout
);
  reg [9:0] shift_reg;
  reg [3:0] count;

  always @(posedge clk or negedge reset)
  begin
    if (!reset)
    begin
      shift_reg <= 10'h0;
      count <= 4'h0;
    end
    else
    begin
      if (shift)
      begin
        shift_reg <= {din, shift_reg[9:1]}; // Shift the bits and input din
        count = count+1;
      end
    end
  end

  // Update dout with the current shift_reg value every cycle
  always @(posedge clk or negedge reset)
  begin
    if (!reset)
    begin
      dout <= 10'h0;
    end
    else
    begin
      dout <= shift_reg; // Always output the current state of the shift register
    end
  end
  
  always @(posedge clk or negedge reset)
    begin
    if(count == 4'h10)
      
      deco <= 1'b1; // Always output the current state of the shift register

  	else
      deco <= 1'b0;
    end
  
  //assign deco = shift;
endmodule

Serdes/piso.sv
module piso (
    input clk,
    input reset,
    input [9:0] din,
    input send_in,
    output reg dout,
    output reg sending // Signal that indicates when PISO is sending data
);

  reg [9:0] shift_reg;

  always @(posedge clk or negedge reset) 
  begin
    if (!reset) 
    begin
      shift_reg <= 10'h0; // Reset shift register
      dout <= 1'b0;       // Clear dout during reset
      sending <= 1'b0;    // Clear sending flag during reset
    end 
    else 
    begin
      if (send_in) 
      begin
        shift_reg <= din; // Load data into shift register
        sending <= 1'b1;  // Indicate that sending has started
      end 
      else if (sending) 
      begin
        dout <= shift_reg[0]; // Output the LSB
        shift_reg <= {1'b0, shift_reg[9:1]}; // Shift right
        
        // If the shift register is empty, stop sending
        if (shift_reg == 10'b0) 
          sending <= 1'b0; 
      end
    end
  end

endmodule
`default_nettype wire

Serdes/encoder.sv
module encoder (
    input clk,
    input reset,
    input [7:0] din,
    input enc_en,
  	output reg piso_en,
    output reg [9:0] dout
);
    reg [3:0] temp_4;
    reg [5:0] temp_6;

    // Asynchronous reset block
    always @(posedge clk or negedge reset) begin
        if (!reset) begin
            temp_4 <= 4'h0;
            temp_6 <= 6'h0;
            dout <= 10'h0; // Reset dout
        end
        else if (!enc_en) begin
            // Encoding logic when enc_en is low
            case (din[7:5])
                3'b000: temp_4 <= 4'b0100;
                3'b001: temp_4 <= 4'b1001;
                3'b010: temp_4 <= 4'b0101;
                3'b011: temp_4 <= 4'b0011;
                3'b100: temp_4 <= 4'b0010;
                3'b101: temp_4 <= 4'b1010;
                3'b110: temp_4 <= 4'b0110;
                3'b111: temp_4 <= 4'b0001;
                default: temp_4 <= 4'b0000;
            endcase
            
            case (din[4:0])
                5'b00000: temp_6 <= 6'b011000;
                5'b00001: temp_6 <= 6'b011101;
                5'b00010: temp_6 <= 6'b010010;
                5'b00011: temp_6 <= 6'b110001;
                5'b00100: temp_6 <= 6'b110101;
                5'b00101: temp_6 <= 6'b101001;
                5'b00110: temp_6 <= 6'b011001;
                5'b00111: temp_6 <= 6'b111000;
                5'b01000: temp_6 <= 6'b111001;
                5'b01001: temp_6 <= 6'b100101;
                5'b01010: temp_6 <= 6'b010101;
                5'b01011: temp_6 <= 6'b110100;
                5'b01100: temp_6 <= 6'b001101;
                5'b01101: temp_6 <= 6'b101100;
                5'b01110: temp_6 <= 6'b011100;
                5'b01111: temp_6 <= 6'b010111;
                5'b10000: temp_6 <= 6'b011011;
                5'b10001: temp_6 <= 6'b100011;
                5'b10010: temp_6 <= 6'b010011;
                5'b10011: temp_6 <= 6'b110010;
                5'b10100: temp_6 <= 6'b001011;
                5'b10101: temp_6 <= 6'b101010;
                5'b10110: temp_6 <= 6'b011010;
                5'b10111: temp_6 <= 6'b111010;
                5'b11000: temp_6 <= 6'b110011;
                5'b11001: temp_6 <= 6'b100110;
                5'b11010: temp_6 <= 6'b010110;
                5'b11011: temp_6 <= 6'b110110;
                5'b11100: temp_6 <= 6'b001110;
                5'b11101: temp_6 <= 6'b101110;
                5'b11110: temp_6 <= 6'b011110;
                5'b11111: temp_6 <= 6'b101011;
                default: temp_6 <= 6'b000000;
            endcase
        end
    end

    // Output assignment based on the encoder enable signal
    always @(posedge clk) begin
        if (enc_en) begin
            dout <= {temp_4, temp_6}; // Update dout when enc_en is high
        end
    end
assign piso_en = enc_en;
endmodule

Serdes/design.sv
// Code your design here
`include "decoder.sv"
`include "encoder.sv"
`include "piso.sv"
`include "sipo.sv"
`include "reg_10.sv"
`include "reg_8.sv"
`include "enable.sv"

module top(
    input           clk,
    input           reset,
    //input           ser_in,
    input           dec_en,
    input           ser_en,
    output wire     ser_out,
    output wire [7:0] dout,
    input [7:0]     din
  );
  
  // Serializer module
  wire data_en = 1'b1;
  wire [7:0]       data_8b_reg_e;
  wire [9:0]       data_10b_enc;
  wire [9:0]       data_10b_reg_e;
  wire ser_in,ser_out;
  wire piso_en;
  reg_8 reg_8_inst_e (
               .clk(clk),
               .reset(reset),
               .din(din),
               .data_en(data_en),
               .dout(data_8b_reg_e)
             );
  
  encoder encoder_inst (
                   .clk(clk),
                   .reset(reset),
                   .din(data_8b_reg_e),
  				  .enc_en(ser_en),
  				  .piso_en(piso_en),
                   .dout(data_10b_enc)
                 );
  

  reg_10 reg_10_inst_e (
                .clk(clk),
                .reset(reset),
                .din(data_10b_enc),
                .data_en(data_en),
                .dout(data_10b_reg_e)
              );
  

  piso piso_inst_e (
               .clk(clk),
               .reset(reset),
               .din(data_10b_reg_e),
   				 .send_in(~piso_en),
  				  .sending(sipo_en),
               .dout(ser_out)
             );

  // Deserializer module
  wire [9:0]       data_10b;
  wire[9:0]	      data_10b_reg_d;
  wire [7:0]       data_8b_dec;
  wire sipo_en,deco_en;

  // Instantiate the SIPO module
  
  sipo sipo_inst_d (
               .clk(clk),
               .reset(reset),
               .din(ser_out),
    			.shift(sipo_en),
  			  .deco(deco_en),
               .dout(data_10b)
             );

  // Instantiate the 10-bit latch
  reg_10 reg_10_inst_d (
                .clk(clk),
                .reset(reset),
                .din(data_10b),
                .data_en(data_en),
                .dout(data_10b_reg_d)
              );

  // Instantiate the 10b/8b decoder
  decoder decoder_inst (
            .clk(clk),
            .reset(reset),
            .din(data_10b_reg_d),
            .dec_en(~deco_en),
            .dout(data_8b_dec)
          );

  // Instantiate the 8-bit latch
  reg_8 reg_8_inst_d (
             .clk(clk),
             .reset(reset),
             .din(data_8b_dec),
             .data_en(data_en),
    		.dout(dout)
           );
endmodule
`default_nettype wire

Serdes/testbench.sv
module tb_top;

    // Clock, Reset, and Control signals
    reg clk;
    reg reset; // Active-low reset
    reg [7:0] data_in; // Two data inputs
    reg [7:0] data_out;
    reg dec_en, ser_en;
    reg ser_out;

    // Instantiate the top module
    top uut (
        .clk(clk),
        .reset(reset), // Connect active-low reset
        .din(data_in),
        .ser_out(ser_out),
        .dec_en(dec_en),
        .ser_en(ser_en),
        .dout(data_out)
    );

    // Clock generation (50 MHz, period = 20 ns)
    always #10 clk = ~clk;

    // Test Vector Variables
    reg [7:0] test_vectors1 [0:15]; // Array for first input test vectors

    // Testbench initialization
    initial begin
        // Initialize the clock and reset
        clk = 0;
        reset = 1; // Active high (inactive)

        // Initialize test vectors and expected output
      test_vectors1[0] = 8'b00100111; 
        test_vectors1[1] = 8'h3C; 
        test_vectors1[2] = 8'h5F; 
        test_vectors1[3] = 8'h99; 
        test_vectors1[4] = 8'hAA; 
        test_vectors1[5] = 8'hFF; 
        test_vectors1[6] = 8'h01; 
        test_vectors1[7] = 8'hC3; 
        test_vectors1[8] = 8'h76; 
        test_vectors1[9] = 8'h44; 
        test_vectors1[10] = 8'h68; 
        test_vectors1[11] = 8'h7E;
        test_vectors1[12] = 8'hB2;
        test_vectors1[13] = 8'h0F;
        test_vectors1[14] = 8'h13;
        test_vectors1[15] = 8'hEF;

        // Apply active-low reset for a few cycles
        #10 reset = 1;  // Active-low reset (asserted)
        #10 reset = 0;  // Deassert the reset (inactive)
      	#10 reset = 1;

        // Wait for pipeline stages to initialize
        #10;  // Wait for the pipeline to stabilize after reset

        // Apply each test vector with delays
        // Test Vector 0
        data_in = test_vectors1[0];
        #100; // Apply inputs
        #100 ser_en = 0;
     	#100 ser_en = 1;
        #100 dec_en = 1;
        #100 dec_en =0;
      
        // Loop to capture serial output
        repeat (8) begin
            #10;  // Wait for the next clock cycle
            $display("Serial Output Bit: %b", ser_out);
        end

        #100; // Wait for output

       // Test Vector 1
        data_in = test_vectors1[1];
        #100; // Apply inputs
        #100 ser_en = 0;
     	#100 ser_en = 1;
        #100 dec_en = 1;
        #100 dec_en =0;
      
        // Loop to capture serial output
        repeat (8) begin
            #10;  // Wait for the next clock cycle
            $display("Serial Output Bit: %b", ser_out);
        end
        #100;
      	// Test Vector 2
      	data_in = test_vectors1[2];
        #100; // Apply inputs
        #100 ser_en = 0;
     	#100 ser_en = 1;
        #100 dec_en = 1;
        #100 dec_en =0;
      
        // Loop to capture serial output
        repeat (8) begin
            #10;  // Wait for the next clock cycle
            $display("Serial Output Bit: %b", ser_out);
        end
        
        #1000; // Wait for output
  
        $stop;
    end

    

    initial begin
        $dumpfile("waveform.vcd"); // Name of the VCD file
        $dumpvars(0, tb_top);       // Dump all variables in the tb_top module
    end
    
endmodule

Serdes/waveform.vcd
$date
	Thu Oct 17 15:36:02 2024
$end

$version
	Synopsys VCS version U-2023.03-SP2_Full64
$end

$timescale
	1ns
$end

$comment Csum: 1 ee30c256fb7033d7 $end


$scope module tb_top $end
$var reg 1 ! clk $end
$var reg 1 " reset $end
$var reg 8 # data_in [7:0] $end
$var reg 8 $ data_out [7:0] $end
$var reg 1 % dec_en $end
$var reg 1 & ser_en $end
$var reg 1 ' ser_out $end

$scope module uut $end
$var wire 1 ! clk $end
$var wire 1 " reset $end
$var wire 1 % dec_en $end
$var wire 1 & ser_en $end
$var wire 1 ' ser_out $end
$var wire 8 $ dout [7:0] $end
$var wire 8 # din [7:0] $end
$var wire 1 ( data_en $end
$var wire 8 ) data_8b_reg_e [7:0] $end
$var wire 10 * data_10b_enc [9:0] $end
$var wire 10 + data_10b_reg_e [9:0] $end
$var wire 1 , ser_in $end
$var wire 1 & piso_en $end
$var wire 1 - sipo_en $end
$var wire 10 . data_10b [9:0] $end
$var wire 10 / data_10b_reg_d [9:0] $end
$var wire 8 0 data_8b_dec [7:0] $end
$var wire 1 1 deco_en $end

$scope module reg_8_inst_e $end
$var wire 1 ! clk $end
$var wire 1 " reset $end
$var wire 1 2 data_en $end
$var wire 8 # din [7:0] $end
$var reg 8 ) dout [7:0] $end
$upscope $end


$scope module encoder_inst $end
$var wire 1 ! clk $end
$var wire 1 " reset $end
$var wire 8 ) din [7:0] $end
$var wire 1 & enc_en $end
$var reg 1 & piso_en $end
$var reg 10 * dout [9:0] $end
$var reg 4 3 temp_4 [3:0] $end
$var reg 6 4 temp_6 [5:0] $end
$upscope $end


$scope module reg_10_inst_e $end
$var wire 1 ! clk $end
$var wire 1 " reset $end
$var wire 1 5 data_en $end
$var wire 10 * din [9:0] $end
$var reg 10 + dout [9:0] $end
$upscope $end


$scope module piso_inst_e $end
$var wire 1 ! clk $end
$var wire 1 " reset $end
$var wire 10 + din [9:0] $end
$var wire 1 6 send_in $end
$var reg 1 ' dout $end
$var reg 1 - sending $end
$var reg 10 7 shift_reg [9:0] $end
$upscope $end


$scope module sipo_inst_d $end
$var wire 1 ! clk $end
$var wire 1 " reset $end
$var wire 1 ' din $end
$var wire 1 - shift $end
$var reg 1 1 deco $end
$var reg 10 . dout [9:0] $end
$var reg 10 8 shift_reg [9:0] $end
$var reg 4 9 count [3:0] $end
$upscope $end


$scope module reg_10_inst_d $end
$var wire 1 ! clk $end
$var wire 1 " reset $end
$var wire 1 : data_en $end
$var wire 10 . din [9:0] $end
$var reg 10 / dout [9:0] $end
$upscope $end


$scope module decoder_inst $end
$var wire 1 ! clk $end
$var wire 1 " reset $end
$var wire 10 / din [9:0] $end
$var wire 1 ; dec_en $end
$var reg 8 0 dout [7:0] $end
$var reg 3 < temp_3 [2:0] $end
$var reg 5 = temp_5 [4:0] $end
$var reg 4 > count [3:0] $end
$upscope $end


$scope module reg_8_inst_d $end
$var wire 1 ! clk $end
$var wire 1 " reset $end
$var wire 1 ? data_en $end
$var wire 8 0 din [7:0] $end
$var reg 8 $ dout [7:0] $end
$upscope $end

$upscope $end

$upscope $end

$enddefinitions $end

#0
$dumpvars
0!
x%
x1
x'
1"
x-
x&
x6
x;
bxxxx 9
bxxxxxxxx #
bxxxxxxxx 0
bxxxxxxxxxx *
bxxxxxxxxxx /
bxxxxxxxxxx +
bxxxxxxxx $
bxxxxxxxx )
bxxxxxxxxxx 7
bxxxxxxxxxx .
bxxxxxxxxxx 8
bxxx <
bxxxx 3
bxxxxx =
bxxxxxx 4
1?
bxxxx >
1:
15
12
z,
1(
$end
#10
1!
01
1;
#20
0!
0"
b00000000 )
b00000000 $
b0000000000 +
b0000000000 /
b0000 3
b000000 4
b0000000000 *
b0000000000 7
0'
0-
b0000000000 8
b0000 9
b0000000000 .
b000 <
b00000 =
b00000000 0
#30
1!
1"
11
0;
bxxxxxxxx )
#40
0!
b00100111 #
#50
1!
b00100111 )
#60
0!
#70
1!
#80
0!
#90
1!
#100
0!
#110
1!
#120
0!
#130
1!
#140
0!
#150
1!
#160
0!
#170
1!
#180
0!
#190
1!
#200
0!
#210
1!
#220
0!
#230
1!
#240
0&
16
0!
#250
1!
b1001 3
b111000 4
1-
#260
0!
#270
1!
b0001 9
#280
0!
#290
1!
b0010 9
01
1;
#300
0!
#310
1!
b0011 9
#320
0!
#330
1!
b0100 9
#340
1&
06
0!
#350
1!
b0101 9
b1001111000 *
0-
#360
0!
#370
1!
b1001111000 +
#380
0!
#390
1!
#400
0!
#410
1!
#420
0!
#430
1!
#440
1%
0!
#450
1!
#460
0!
#470
1!
#480
0!
#490
1!
#500
0!
#510
1!
#520
0!
#530
1!
#540
0%
0!
#550
1!
#560
0!
#570
1!
#580
0!
#590
1!
#600
0!
#610
1!
#620
0!
#630
1!
#640
0!
#650
1!
#660
0!
#670
1!
#680
0!
#690
1!
#700
0!
#710
1!
#720
b00111100 #
0!
#730
1!
b00111100 )
#740
0!
#750
1!
#760
0!
#770
1!
#780
0!
#790
1!
#800
0!
#810
1!
#820
0!
#830
1!
#840
0!
#850
1!
#860
0!
#870
1!
#880
0!
#890
1!
#900
0!
#910
1!
#920
0&
16
0!
#930
1!
b001110 4
b1001111000 7
1-
#940
0!
#950
1!
b0110 9
#960
0!
#970
1!
b0111 9
#980
0!
#990
1!
b1000 9
#1000
0!
#1010
1!
b1001 9
#1020
1&
06
0!
#1030
1!
b1010 9
b1001001110 *
b0100111100 7
#1040
0!
#1050
1!
b1011 9
b1001001110 +
b0010011110 7
#1060
0!
#1070
1!
b1100 9
b0001001111 7
#1080
0!
#1090
1!
b1101 9
1'
b0000100111 7
#1100
0!
#1110
1!
b1110 9
b0000010011 7
b1000000000 8
#1120
1%
0!
#1130
1!
b1111 9
b1000000000 .
b0000001001 7
b1100000000 8
#1140
0!
#1150
1!
b0000 9
b1000000000 /
b1100000000 .
b0000000100 7
b1110000000 8
#1160
0!
#1170
1!
b0001 9
11
0;
b1100000000 /
b1110000000 .
0'
b0000000010 7
b1111000000 8
#1180
0!
#1190
1!
b0010 9
01
1;
b1110000000 /
b1111000000 .
b0000000001 7
b0111100000 8
#1200
0!
#1210
1!
b0011 9
b1111000000 /
b0111100000 .
1'
b0000000000 7
b0011110000 8
#1220
0%
0!
#1230
1!
b0100 9
b0111100000 /
b0011110000 .
0'
0-
b1001111000 8
#1240
0!
#1250
1!
b0011110000 /
b1001111000 .
#1260
0!
#1270
1!
b1001111000 /
b011 <
#1280
0!
#1290
1!
b001 <
b00111 =
b01100000 0
#1300
0!
#1310
1!
b01100000 $
b00100111 0
#1320
0!
#1330
1!
b00100111 $
#1340
0!
#1350
1!
#1360
0!
#1370
1!
#1380
0!
#1390
1!
#1400
b01011111 #
0!
#1410
1!
b01011111 )
#1420
0!
#1430
1!
#1440
0!
#1450
1!
#1460
0!
#1470
1!
#1480
0!
#1490
1!
#1500
0!
#1510
1!
#1520
0!
#1530
1!
#1540
0!
#1550
1!
#1560
0!
#1570
1!
#1580
0!
#1590
1!
#1600
0&
16
0!
#1610
1!
b0101 3
b101011 4
b1001001110 7
1-
#1620
0!
#1630
1!
b0101 9
b0100111100 8
#1640
0!
#1650
1!
b0110 9
b0100111100 .
b0010011110 8
#1660
0!
#1670
1!
b0111 9
b0100111100 /
b0010011110 .
b0001001111 8
#1680
0!
#1690
1!
b1000 9
b0010011110 /
b0001001111 .
b0000100111 8
b000 <
b00000 =
#1700
1&
06
0!
#1710
1!
b1001 9
b0001001111 /
b0000100111 .
b0101101011 *
b0100100111 7
b0000010011 8
b100 <
b11110 =
b00000000 0
#1720
0!
#1730
1!
b1010 9
b00000000 $
b0101101011 +
b0000100111 /
b0000010011 .
1'
b0010010011 7
b0000001001 8
b111 <
b00000 =
b10011110 0
#1740
0!
#1750
1!
b1011 9
b10011110 $
b0000010011 /
b0000001001 .
b0001001001 7
b1000000100 8
b000 <
b11100000 0
#1760
0!
#1770
1!
b1100 9
b11100000 $
b0000001001 /
b1000000100 .
b0000100100 7
b1100000010 8
b10010 =
b00000000 0
#1780
0!
#1790
1!
b1101 9
b00000000 $
b1000000100 /
b1100000010 .
0'
b0000010010 7
b1110000001 8
b00000 =
b00010010 0
#1800
1%
0!
#1810
1!
b1110 9
b00010010 $
b1100000010 /
b1110000001 .
b0000001001 7
b0111000000 8
b00000000 0
#1820
0!
#1830
1!
b1111 9
b00000000 $
b1110000001 /
b0111000000 .
1'
b0000000100 7
b0011100000 8
#1840
0!
#1850
1!
b0000 9
b0111000000 /
b0011100000 .
0'
b0000000010 7
b1001110000 8
#1860
0!
#1870
1!
b0001 9
11
0;
b0011100000 /
b1001110000 .
b0000000001 7
b0100111000 8
#1880
0!
#1890
1!
b0010 9
01
1;
b1001110000 /
b0100111000 .
1'
b0000000000 7
b0010011100 8
#1900
0%
0!
#1910
1!
b0011 9
b0100111000 /
b0010011100 .
0'
0-
b1001001110 8
b001 <
#1920
0!
#1930
1!
b0010011100 /
b1001001110 .
b000 <
b00111 =
b00100000 0
#1940
0!
#1950
1!
b00100000 $
b1001001110 /
b100 <
b01110 =
b00000111 0
#1960
0!
#1970
1!
b00000111 $
b001 <
b11100 =
b10001110 0
#1980
0!
#1990
1!
b10001110 $
b00111100 0
#2000
0!
#2010
1!
b00111100 $
